run.py
cli/__init__.py
cli/commands/__init__.py
cli/commands/command.py
connor/__init__.py
connor/processes.py
connor/reader.py
connor/tree_builder.py
connor/data/config.ini
connor/fonts/Coder's Crux.ttf
connor/static/style.css
connor/static/icons/clear.png
connor/static/icons/folder.png
connor/static/icons/refresh.png
connor/static/icons/upload.png
connor/tmp/keep.txt
gui/__init__.py
gui/views/__init__.py
gui/views/about.py
gui/views/organizer.py
gui/views/settings.py
connor_nlp-1.0.0.dist-info/LICENSE
connor_nlp-1.0.0.dist-info/METADATA
connor_nlp-1.0.0.dist-info/WHEEL
connor_nlp-1.0.0.dist-info/entry_points.txt
connor_nlp-1.0.0.dist-info/top_level.txt
connor_nlp-1.0.0.dist-info/RECORD
