Metadata-Version: 2.1
Name: connor_nlp
Version: 1.0.0
Summary: Fast and fully local NLP file organizer that organizes files based on their content.
Home-page: https://github.com/ycatsh/connor
Author: Ycatsh
License: MIT
Classifier: Programming Language :: Python :: 3
Classifier: License :: OSI Approved :: MIT License
Classifier: Operating System :: OS Independent
Requires-Python: >=3.10
License-File: LICENSE
Requires-Dist: docx ==0.2.4
Requires-Dist: python-pptx ==1.0.2
Requires-Dist: python-docx ==0.8.11
Requires-Dist: nltk ==3.9.1
Requires-Dist: numpy ==2.1.3
Requires-Dist: odfpy ==1.4.1
Requires-Dist: openpyxl ==3.1.5
Requires-Dist: PyPDF2 ==3.0.1
Requires-Dist: PyQt6 ==6.7.1
Requires-Dist: scikit-learn ==1.5.2
Requires-Dist: sentence-transformers ==3.3.1
